{
	"TVL": 1049930.3651492903,
	"totalSupply": 1894293.3079689539,
	"totalBorrow": 844362.9428196638,
	"pools": [
		{
			"id": "0x79b56CB219901DBF42bB5951a0eDF27465F96206",
			"TVL": 916499.600271328,
			"totalSupply": 1614897.1434960105,
			"totalNFTSupply": 0,
			"totalBorrow": 698397.5432246823,
			"markets": {
				"ETH": {
					"id": "0x4aE7413182849D062B72518928a4b2DE87F0e411",
					"exchangeRate": 0.023944387589113176,
					"supply": 181.9697710491109,
					"borrow": 169.96225848102358,
					"reserves": 1.1129340497950504,
					"priceETH": 1,
					"priceUSD": 1893.91454,
					"cash": 13.120446617882365,
					"cashUSD": 24849.004620901236,
					"collateralFactor": 0.9,
					"borrowLimit": 0.765
				},
				"USDC": {
					"id": "0x3fed9C8b527fA6299b3044E5178ACc34eC2e25e2",
					"exchangeRate": 0.0320816582530434,
					"supply": 295098.34936999914,
					"borrow": 301968.938468,
					"reserves": 6870.589098,
					"priceETH": 0.0005280069289715681,
					"priceUSD": 1,
					"cash": 0,
					"cashUSD": 0,
					"collateralFactor": 0.8,
					"borrowLimit": 0.68
				},
				"WBTC": {
					"id": "0xdb6994189DB5f14A9261CF0420cC377BADaB03bE",
					"exchangeRate": 0.022936325679318373,
					"supply": 2.09953241,
					"borrow": 1.89746503,
					"reserves": 0.00767403,
					"priceETH": 15.765888253859648,
					"priceUSD": 29859.245,
					"cash": 0.20974141,
					"cashUSD": 6262.720147835449,
					"collateralFactor": 0.9,
					"borrowLimit": 0.765
				},
				"ENJ": {
					"id": "0x28af5F61544916d33C4105eb536c9177f5523b67",
					"exchangeRate": 0.02144077033200437,
					"supply": 39328.19503501619,
					"borrow": 40710.969856771735,
					"reserves": 1383.2422116122766,
					"priceETH": 0.000166069012270661,
					"priceUSD": 0.3145205169828433,
					"cash": 0.46738985673873507,
					"cashUSD": 0.147003699374004,
					"collateralFactor": 0.6,
					"borrowLimit": 0.51
				},
				"MATIC": {
					"id": "0x54C312ba0B974d56e2c532Ca407FfDA2c6a14793",
					"exchangeRate": 0.020342116010656476,
					"supply": 520.5408685615453,
					"borrow": 257.97594172172035,
					"reserves": 13.634627186276397,
					"priceETH": 0.0003921253701341772,
					"priceUSD": 0.74265194,
					"cash": 276.1995540261013,
					"cashUSD": 205.12013462461894,
					"collateralFactor": 0.7,
					"borrowLimit": 0.595
				},
				"DOP": {
					"id": "0xAa08183a98b10BBAdb9CCAa852319382120D4683",
					"exchangeRate": 0.020267329469166977,
					"supply": 3245905.900817447,
					"borrow": 17612.13202661852,
					"reserves": 622.9478370706087,
					"priceETH": 0.0001463525583515733,
					"priceUSD": 0.2771792382282431,
					"cash": 3228916.716627899,
					"cashUSD": 894988.6758173609,
					"collateralFactor": 0.75,
					"borrowLimit": 0.6375
				},
				"GOHM": {
					"id": "0x6020D8630DD312748023b5D0263a49f5de729BF6",
					"exchangeRate": 2e-14,
					"supply": 0.006811466856388676,
					"borrow": 0,
					"reserves": 0,
					"priceETH": 1.4973571526285145,
					"priceUSD": 2835.866482936143,
					"cash": 0.006811466856388675,
					"cashUSD": 19.316410557663055,
					"collateralFactor": 0.8,
					"borrowLimit": 0.68
				}
			},
			"lendRates": {
				"ETH": {
					"apy": 0.174580592045544,
					"apr": 0.1619948291421922,
					"tokenSymbol": "ETH"
				},
				"USDC": {
					"apy": 0.410216980667256,
					"apr": 0.34871424680457164,
					"tokenSymbol": "USDC"
				},
				"WBTC": {
					"apy": 0.140212149187536,
					"apr": 0.13193434625343148,
					"tokenSymbol": "WBTC"
				},
				"ENJ": {
					"apy": 0.37630529569623605,
					"apr": 0.32369130349892306,
					"tokenSymbol": "ENJ"
				},
				"MATIC": {
					"apy": 0.013830703834572,
					"apr": 0.013743796980630663,
					"tokenSymbol": "MATIC"
				},
				"DOP": {
					"apy": 0.00025005606588,
					"apr": 0.0002500274117744894,
					"tokenSymbol": "DOP"
				},
				"GOHM": {
					"apy": 0,
					"apr": 0,
					"tokenSymbol": "GOHM"
				}
			},
			"borrowRates": {
				"ETH": {
					"apy": 0.267020544516192,
					"apr": 0.2390173599617631,
					"tokenSymbol": "ETH"
				},
				"USDC": {
					"apy": 0.400923555714036,
					"apr": 0.3419121051644085,
					"tokenSymbol": "USDC"
				},
				"WBTC": {
					"apy": 0.221634012332268,
					"apr": 0.20186846485822052,
					"tokenSymbol": "WBTC"
				},
				"ENJ": {
					"apy": 0.519319770357204,
					"apr": 0.4256374694357712,
					"tokenSymbol": "ENJ"
				},
				"MATIC": {
					"apy": 0.039867762970944,
					"apr": 0.03915730270274853,
					"tokenSymbol": "MATIC"
				},
				"DOP": {
					"apy": 0.076808650912848,
					"apr": 0.074230360785708,
					"tokenSymbol": "DOP"
				},
				"GOHM": {
					"apy": 0.000999999997884,
					"apr": 0.0009995419571628972,
					"tokenSymbol": "GOHM"
				}
			}
		},
		{
			"id": "0xB70FB69a522ed8D4613C4C720F91F93a836EE2f5",
			"TVL": 77432.56476960961,
			"totalSupply": 205729.5947939773,
			"totalNFTSupply": 72680.0310646424,
			"totalBorrow": 128297.03002436769,
			"markets": {
				"ETH": {
					"id": "0xD72929e284E8bc2f7458A6302bE961B91bccB339",
					"exchangeRate": 0.022302788932582588,
					"supply": 58.586519186517734,
					"borrow": 57.758166569843056,
					"reserves": 0.8200078597605545,
					"priceETH": 1,
					"priceUSD": 1893.91454,
					"cash": 1.6483604764352304,
					"cashUSD": 3121.8538734820104,
					"collateralFactor": 0.85,
					"borrowLimit": 0.7225
				},
				"USDC": {
					"id": "0x7489c6BaAba57d9a431642b26E034aCD191039f7",
					"exchangeRate": 0.0229066754323665,
					"supply": 22090.70319399999,
					"borrow": 18907.998554,
					"reserves": 94.623293,
					"priceETH": 0.0005280069289715681,
					"priceUSD": 1,
					"cash": 3277.327933,
					"cashUSD": 3277.327933,
					"collateralFactor": 0,
					"borrowLimit": 0
				},
				"MOONBIRD": {
					"id": "0x397d11F822578B37b10582db5BCEb43BF6E7C85b",
					"exchangeRate": 100000000,
					"supply": 0,
					"borrow": 0,
					"reserves": 0,
					"priceETH": 1.6500000000000001,
					"priceUSD": 3124.9589910000004,
					"cash": 0,
					"cashUSD": 0,
					"collateralFactor": 0.65,
					"borrowLimit": 0.5525
				},
				"FIPUNKS": {
					"id": "0x3786f8aB0A0652E23C6503A9a44322B3295608fE",
					"exchangeRate": 100000000,
					"supply": 0,
					"borrow": 0,
					"reserves": 0,
					"priceETH": 49.82011425881019,
					"priceUSD": 94355.03877922194,
					"cash": 0,
					"cashUSD": 0,
					"collateralFactor": 0.75,
					"borrowLimit": 0.6375
				},
				"BAYC": {
					"id": "0xC3D8e1fD31e55EDe71aE1453dDf858461E23B59a",
					"exchangeRate": 100000000,
					"supply": 1,
					"borrow": 0,
					"reserves": 0,
					"priceETH": 32.68,
					"priceUSD": 61893.1271672,
					"cash": 1,
					"cashUSD": 61893.1271672,
					"collateralFactor": 0.75,
					"borrowLimit": 0.6375
				},
				"MAYC": {
					"id": "0x397a7E7710F3a074dA1B6823E94047E57A5db896",
					"exchangeRate": 100000000,
					"supply": 0,
					"borrow": 0,
					"reserves": 0,
					"priceETH": 6.07,
					"priceUSD": 11496.0612578,
					"cash": 0,
					"cashUSD": 0,
					"collateralFactor": 0.7,
					"borrowLimit": 0.595
				},
				"OTHR": {
					"id": "0x109D97019EdA5e32B31Cd995Ba3D29FC5A3e7c97",
					"exchangeRate": 100000000,
					"supply": 3,
					"borrow": 0,
					"reserves": 0,
					"priceETH": 0.6425200000000001,
					"priceUSD": 1216.8779702408,
					"cash": 3,
					"cashUSD": 3650.6339107224003,
					"collateralFactor": 0.7,
					"borrowLimit": 0.595
				},
				"LAND": {
					"id": "0x5188510a48e8F716e80338c2a2AD4FC415aFC290",
					"exchangeRate": 100000000,
					"supply": 1,
					"borrow": 0,
					"reserves": 0,
					"priceETH": 0.3,
					"priceUSD": 568.174362,
					"cash": 1,
					"cashUSD": 568.174362,
					"collateralFactor": 0.65,
					"borrowLimit": 0.5525
				},
				"CLONEX": {
					"id": "0x57789a12fc3236b12201fAbCd7c8B7Cbb6A94727",
					"exchangeRate": 100000000,
					"supply": 2,
					"borrow": 0,
					"reserves": 0,
					"priceETH": 1.734,
					"priceUSD": 3284.04781236,
					"cash": 2,
					"cashUSD": 6568.09562472,
					"collateralFactor": 0.65,
					"borrowLimit": 0.5525
				},
				"⚇": {
					"id": "0x69de3C627561F6A3A260e89c43C566C1F3c93E23",
					"exchangeRate": 100000000,
					"supply": 0,
					"borrow": 0,
					"reserves": 0,
					"priceETH": 1.2638200000000002,
					"priceUSD": 2393.5670739428,
					"cash": 0,
					"cashUSD": 0,
					"collateralFactor": 0.65,
					"borrowLimit": 0.5525
				},
				"AZUKI": {
					"id": "0xCfC8AfAC17d92796809a4b38a74A245011a96E83",
					"exchangeRate": 100000000,
					"supply": 0,
					"borrow": 0,
					"reserves": 0,
					"priceETH": 5.979000000000001,
					"priceUSD": 11323.715034660001,
					"cash": 0,
					"cashUSD": 0,
					"collateralFactor": 0.7,
					"borrowLimit": 0.595
				},
				"DOODLE": {
					"id": "0x5c2cBa783f2BE59849ee1B01fFbF1ed768B444e0",
					"exchangeRate": 100000000,
					"supply": 0,
					"borrow": 0,
					"reserves": 0,
					"priceETH": 1.416350968408029,
					"priceUSD": 2682.447692811047,
					"cash": 0,
					"cashUSD": 0,
					"collateralFactor": 0,
					"borrowLimit": 0
				},
				"BAKC": {
					"id": "0x43244977Fae5ae5e2979533d5F0221D80840Fa1A",
					"exchangeRate": 100000000,
					"supply": 0,
					"borrow": 0,
					"reserves": 0,
					"priceETH": 2.3989,
					"priceUSD": 4543.311590005999,
					"cash": 0,
					"cashUSD": 0,
					"collateralFactor": 0.6,
					"borrowLimit": 0.51
				},
				"FRAX": {
					"id": "0x03e1Eb147aB39d744565Ca1CEc4b03106D21Fa92",
					"exchangeRate": 0.02,
					"supply": 0,
					"borrow": 0,
					"reserves": 0,
					"priceETH": 0.0005274780349909558,
					"priceUSD": 0.99899832,
					"cash": 0,
					"cashUSD": 0,
					"collateralFactor": 0,
					"borrowLimit": 0
				},
				"XPUNK": {
					"id": "0xfBA58fDDB88203E1D32D0F3E6DbFD9d8b505EC18",
					"exchangeRate": 4.0000000000000004e-11,
					"supply": 0,
					"borrow": 0,
					"reserves": 0,
					"priceETH": 51.9030303145598,
					"priceUSD": 98299.90378280557,
					"cash": 0,
					"cashUSD": 0,
					"collateralFactor": 0,
					"borrowLimit": 0
				},
				"XMEEB": {
					"id": "0x8486B523a32e9D0d021078Fe68a3b98fC765FbaB",
					"exchangeRate": 4.0000000000000004e-11,
					"supply": 0,
					"borrow": 0,
					"reserves": 0,
					"priceETH": 1.4639363156630747,
					"priceUSD": 2772.5702738683267,
					"cash": 0,
					"cashUSD": 0,
					"collateralFactor": 0,
					"borrowLimit": 0
				},
				"XPUNKWETH": {
					"id": "0x3724891050b8b6F9D0B889Ec1B9c89E1673E3f5a",
					"exchangeRate": 4.0000000000000004e-11,
					"supply": 0,
					"borrow": 0,
					"reserves": 0,
					"priceETH": 14.84320099902984,
					"priceUSD": 28111.75419220514,
					"cash": 0,
					"cashUSD": 0,
					"collateralFactor": 0,
					"borrowLimit": 0
				},
				"XMEEBWETH": {
					"id": "0xd4224B4f05067278221f1651e07a2aa5Ca39590E",
					"exchangeRate": 4.0000000000000004e-11,
					"supply": 0,
					"borrow": 0,
					"reserves": 0,
					"priceETH": 2.3327569595574054,
					"priceUSD": 4418.042323991962,
					"cash": 0,
					"cashUSD": 0,
					"collateralFactor": 0,
					"borrowLimit": 0
				},
				"DEGODS": {
					"id": "0x8d39B065BCfA9d86fEDD4CaB6aDa4F6Bc0195D50",
					"exchangeRate": 100000000,
					"supply": 0,
					"borrow": 0,
					"reserves": 0,
					"priceETH": 8.898,
					"priceUSD": 16852.05157692,
					"cash": 0,
					"cashUSD": 0,
					"collateralFactor": 0.6,
					"borrowLimit": 0.51
				},
				"WPUNKS": {
					"id": "0xe3c4582C660Ae527023682F43900d8a89F98D392",
					"exchangeRate": 100000000,
					"supply": 0,
					"borrow": 0,
					"reserves": 0,
					"priceETH": 49.82011425881019,
					"priceUSD": 94355.03877922194,
					"cash": 0,
					"cashUSD": 0,
					"collateralFactor": 0.75,
					"borrowLimit": 0.6375
				},
				"USDT": {
					"id": "0xb4F88dc4783D7395bBC1B8cE64C66580Cde3c13A",
					"exchangeRate": 0.02,
					"supply": 1,
					"borrow": 0,
					"reserves": 0,
					"priceETH": 0.0005280069289715681,
					"priceUSD": 1,
					"cash": 1,
					"cashUSD": 1,
					"collateralFactor": 0,
					"borrowLimit": 0
				},
				"REMILIO": {
					"id": "0x7da479d70245E30Beffd4968d9019953446F9591",
					"exchangeRate": 100000000,
					"supply": 0,
					"borrow": 0,
					"reserves": 0,
					"priceETH": 0.68599,
					"priceUSD": 1299.2064352946,
					"cash": 0,
					"cashUSD": 0,
					"collateralFactor": 0.5,
					"borrowLimit": 0.425
				}
			},
			"lendRates": {
				"ETH": {
					"apy": 0.414773500582008,
					"apr": 0.3520343037024105,
					"tokenSymbol": "ETH"
				},
				"USDC": {
					"apy": 0.09637367188968,
					"apr": 0.09236170370496666,
					"tokenSymbol": "USDC"
				},
				"MOONBIRD": {
					"apy": 0,
					"apr": 0,
					"tokenSymbol": "MOONBIRD"
				},
				"FIPUNKS": {
					"apy": 0,
					"apr": 0,
					"tokenSymbol": "FIPUNKS"
				},
				"BAYC": {
					"apy": 0,
					"apr": 0,
					"tokenSymbol": "BAYC"
				},
				"MAYC": {
					"apy": 0,
					"apr": 0,
					"tokenSymbol": "MAYC"
				},
				"OTHR": {
					"apy": 0,
					"apr": 0,
					"tokenSymbol": "OTHR"
				},
				"LAND": {
					"apy": 0,
					"apr": 0,
					"tokenSymbol": "LAND"
				},
				"CLONEX": {
					"apy": 0,
					"apr": 0,
					"tokenSymbol": "CLONEX"
				},
				"⚇": {
					"apy": 0,
					"apr": 0,
					"tokenSymbol": "⚇"
				},
				"AZUKI": {
					"apy": 0,
					"apr": 0,
					"tokenSymbol": "AZUKI"
				},
				"DOODLE": {
					"apy": 0,
					"apr": 0,
					"tokenSymbol": "DOODLE"
				},
				"BAKC": {
					"apy": 0,
					"apr": 0,
					"tokenSymbol": "BAKC"
				},
				"FRAX": {
					"apy": 0,
					"apr": 0,
					"tokenSymbol": "FRAX"
				},
				"XPUNK": {
					"apy": 0,
					"apr": 0,
					"tokenSymbol": "XPUNK"
				},
				"XMEEB": {
					"apy": 0,
					"apr": 0,
					"tokenSymbol": "XMEEB"
				},
				"XPUNKWETH": {
					"apy": 0,
					"apr": 0,
					"tokenSymbol": "XPUNKWETH"
				},
				"XMEEBWETH": {
					"apy": 0,
					"apr": 0,
					"tokenSymbol": "XMEEBWETH"
				},
				"DEGODS": {
					"apy": 0,
					"apr": 0,
					"tokenSymbol": "DEGODS"
				},
				"WPUNKS": {
					"apy": 0,
					"apr": 0,
					"tokenSymbol": "WPUNKS"
				},
				"USDT": {
					"apy": 0,
					"apr": 0,
					"tokenSymbol": "USDT"
				},
				"REMILIO": {
					"apy": 0,
					"apr": 0,
					"tokenSymbol": "REMILIO"
				}
			},
			"borrowRates": {
				"ETH": {
					"apy": 0.420722074351584,
					"apr": 0.356353944968836,
					"tokenSymbol": "ETH"
				},
				"USDC": {
					"apy": 0.160851215231712,
					"apr": 0.1500843438367383,
					"tokenSymbol": "USDC"
				},
				"MOONBIRD": {
					"apy": 0,
					"apr": 0,
					"tokenSymbol": "MOONBIRD"
				},
				"FIPUNKS": {
					"apy": 0,
					"apr": 0,
					"tokenSymbol": "FIPUNKS"
				},
				"BAYC": {
					"apy": 0,
					"apr": 0,
					"tokenSymbol": "BAYC"
				},
				"MAYC": {
					"apy": 0,
					"apr": 0,
					"tokenSymbol": "MAYC"
				},
				"OTHR": {
					"apy": 0,
					"apr": 0,
					"tokenSymbol": "OTHR"
				},
				"LAND": {
					"apy": 0,
					"apr": 0,
					"tokenSymbol": "LAND"
				},
				"CLONEX": {
					"apy": 0,
					"apr": 0,
					"tokenSymbol": "CLONEX"
				},
				"⚇": {
					"apy": 0,
					"apr": 0,
					"tokenSymbol": "⚇"
				},
				"AZUKI": {
					"apy": 0,
					"apr": 0,
					"tokenSymbol": "AZUKI"
				},
				"DOODLE": {
					"apy": 0,
					"apr": 0,
					"tokenSymbol": "DOODLE"
				},
				"BAKC": {
					"apy": 0,
					"apr": 0,
					"tokenSymbol": "BAKC"
				},
				"FRAX": {
					"apy": 0.02499999999966,
					"apr": 0.024718035237782487,
					"tokenSymbol": "FRAX"
				},
				"XPUNK": {
					"apy": 0.07499999999898,
					"apr": 0.0725390282905467,
					"tokenSymbol": "XPUNK"
				},
				"XMEEB": {
					"apy": 0.07499999999898,
					"apr": 0.0725390282905467,
					"tokenSymbol": "XMEEB"
				},
				"XPUNKWETH": {
					"apy": 0.07499999999898,
					"apr": 0.0725390282905467,
					"tokenSymbol": "XPUNKWETH"
				},
				"XMEEBWETH": {
					"apy": 0.07499999999898,
					"apr": 0.0725390282905467,
					"tokenSymbol": "XMEEBWETH"
				},
				"DEGODS": {
					"apy": 0,
					"apr": 0,
					"tokenSymbol": "DEGODS"
				},
				"WPUNKS": {
					"apy": 0,
					"apr": 0,
					"tokenSymbol": "WPUNKS"
				},
				"USDT": {
					"apy": 0.02499999999966,
					"apr": 0.024718035237782487,
					"tokenSymbol": "USDT"
				},
				"REMILIO": {
					"apy": 0,
					"apr": 0,
					"tokenSymbol": "REMILIO"
				}
			}
		},
		{
			"id": "0x9dEb56b9DD04822924B90ad15d01EE50415f8bC7",
			"TVL": 34728.06159769399,
			"totalSupply": 52386.25254474026,
			"totalNFTSupply": 34947.079266442,
			"totalBorrow": 17658.19094704627,
			"markets": {
				"ETH": {
					"id": "0x0a1EF7feD1B691253F9367daf682BA08A9D2fD9C",
					"exchangeRate": 0.02106358026118691,
					"supply": 9.208004326477294,
					"borrow": 9.323647173143447,
					"reserves": 0.11864542458409907,
					"priceETH": 1,
					"priceUSD": 1893.91454,
					"cash": 0.003002577917944986,
					"cashUSD": 5.686625976278935,
					"collateralFactor": 0,
					"borrowLimit": 0
				},
				"CYBERBROKERS": {
					"id": "0x83355362ebb2180873844523044c866170f9D99C",
					"exchangeRate": 100000000,
					"supply": 36,
					"borrow": 0,
					"reserves": 0,
					"priceETH": 0.23650000000000002,
					"priceUSD": 447.91078871,
					"cash": 36,
					"cashUSD": 16124.78839356,
					"collateralFactor": 0.55,
					"borrowLimit": 0.4675000000000001
				},
				"GOBLIN": {
					"id": "0x65DA0A824269E43A2Fc9586Ef2fFE2aE722C33Be",
					"exchangeRate": 100000000,
					"supply": 0,
					"borrow": 0,
					"reserves": 0,
					"priceETH": 0.3199,
					"priceUSD": 605.8632613460001,
					"cash": 0,
					"cashUSD": 0,
					"collateralFactor": 0,
					"borrowLimit": 0
				},
				"LOBS": {
					"id": "0xCE072AAAEE46FDb3B0aA0Be0516b9491aD88eC57",
					"exchangeRate": 100000000,
					"supply": 0,
					"borrow": 0,
					"reserves": 0,
					"priceETH": 0.8959999,
					"priceUSD": 1696.947238448546,
					"cash": 0,
					"cashUSD": 0,
					"collateralFactor": 0,
					"borrowLimit": 0
				},
				"TOADZ": {
					"id": "0xE9E374eF997D9ee38D705caBAC5B94f469506966",
					"exchangeRate": 100000000,
					"supply": 0,
					"borrow": 0,
					"reserves": 0,
					"priceETH": 0.676706001938055,
					"priceUSD": 1281.6233363757506,
					"cash": 0,
					"cashUSD": 0,
					"collateralFactor": 0,
					"borrowLimit": 0
				},
				"BEANZ": {
					"id": "0xe63D394953908c3EDA007Cf4A94F9352Bb22dEC0",
					"exchangeRate": 100000000,
					"supply": 0,
					"borrow": 0,
					"reserves": 0,
					"priceETH": 0.37849999999999995,
					"priceUSD": 716.8466533899999,
					"cash": 0,
					"cashUSD": 0,
					"collateralFactor": 0.55,
					"borrowLimit": 0.4675000000000001
				},
				"WIZARDS": {
					"id": "0x777a91c5E1CAE1533e32Fe8eD5667022A1E0fbB6",
					"exchangeRate": 100000000,
					"supply": 0,
					"borrow": 0,
					"reserves": 0,
					"priceETH": 1.1764999999999999,
					"priceUSD": 2228.1904563099997,
					"cash": 0,
					"cashUSD": 0,
					"collateralFactor": 0.5,
					"borrowLimit": 0.425
				},
				"CDB": {
					"id": "0xB589a8E4D5c47B721fd7e3dEF994c819Ab8718C4",
					"exchangeRate": 100000000,
					"supply": 1,
					"borrow": 0,
					"reserves": 0,
					"priceETH": 1.16936,
					"priceUSD": 2214.6679064944,
					"cash": 1,
					"cashUSD": 2214.6679064944,
					"collateralFactor": 0.5,
					"borrowLimit": 0.425
				},
				"USDC": {
					"id": "0xDf55F91f8f13F6b3754bf07C6eBDF16C99f83198",
					"exchangeRate": 0.02,
					"supply": 0,
					"borrow": 0,
					"reserves": 0,
					"priceETH": 0.0005280069289715681,
					"priceUSD": 1,
					"cash": 0,
					"cashUSD": 0,
					"collateralFactor": 0,
					"borrowLimit": 0
				},
				"FRAX": {
					"id": "0x140128b2e6562713051df4858ff52f26795B8920",
					"exchangeRate": 0.02,
					"supply": 0,
					"borrow": 0,
					"reserves": 0,
					"priceETH": 0.0005274780349909558,
					"priceUSD": 0.99899832,
					"cash": 0,
					"cashUSD": 0,
					"collateralFactor": 0,
					"borrowLimit": 0
				},
				"MIL": {
					"id": "0x5dAaBd53214046c108BDdC91766FFFee9397cEE4",
					"exchangeRate": 100000000,
					"supply": 3,
					"borrow": 0,
					"reserves": 0,
					"priceETH": 2.9229800000000004,
					"priceUSD": 5535.874322129201,
					"cash": 3,
					"cashUSD": 16607.6229663876,
					"collateralFactor": 0.65,
					"borrowLimit": 0.5525
				},
				"XMILADY": {
					"id": "0x67c06bc0E1C1c4E4617cd293D1F3bcB39244A859",
					"exchangeRate": 4.0000000000000004e-11,
					"supply": 0,
					"borrow": 0,
					"reserves": 0,
					"priceETH": 4.920437238858071,
					"priceUSD": 9318.887629830753,
					"cash": 0,
					"cashUSD": 0,
					"collateralFactor": 0,
					"borrowLimit": 0
				},
				"XWIZARD": {
					"id": "0xF19e040255f3842c009237e0be5A73283371C8df",
					"exchangeRate": 4.0000000000000004e-11,
					"supply": 0,
					"borrow": 0,
					"reserves": 0,
					"priceETH": 0.9505978969277576,
					"priceUSD": 1800.3511786849015,
					"cash": 0,
					"cashUSD": 0,
					"collateralFactor": 0,
					"borrowLimit": 0
				},
				"XMILADYWETH": {
					"id": "0x09dC75D014876381Ef04D1Ef791Af4318f758eBE",
					"exchangeRate": 4.0000000000000004e-11,
					"supply": 0,
					"borrow": 0,
					"reserves": 0,
					"priceETH": 3.7770115747176063,
					"priceUSD": 7153.337139105971,
					"cash": 0,
					"cashUSD": 0,
					"collateralFactor": 0,
					"borrowLimit": 0
				},
				"XWIZARDWETH": {
					"id": "0x92B9CA3F147B485Dae876AC3585cAaDB58962baF",
					"exchangeRate": 4.0000000000000004e-11,
					"supply": 0,
					"borrow": 0,
					"reserves": 0,
					"priceETH": 1.8946986499285858,
					"priceUSD": 3588.3973220181188,
					"cash": 0,
					"cashUSD": 0,
					"collateralFactor": 0,
					"borrowLimit": 0
				}
			},
			"lendRates": {
				"ETH": {
					"apy": 0.33605062243462797,
					"apr": 0.29324363602296,
					"tokenSymbol": "ETH"
				},
				"CYBERBROKERS": {
					"apy": 0,
					"apr": 0,
					"tokenSymbol": "CYBERBROKERS"
				},
				"GOBLIN": {
					"apy": 0,
					"apr": 0,
					"tokenSymbol": "GOBLIN"
				},
				"LOBS": {
					"apy": 0,
					"apr": 0,
					"tokenSymbol": "LOBS"
				},
				"TOADZ": {
					"apy": 0,
					"apr": 0,
					"tokenSymbol": "TOADZ"
				},
				"BEANZ": {
					"apy": 0,
					"apr": 0,
					"tokenSymbol": "BEANZ"
				},
				"WIZARDS": {
					"apy": 0,
					"apr": 0,
					"tokenSymbol": "WIZARDS"
				},
				"CDB": {
					"apy": 0,
					"apr": 0,
					"tokenSymbol": "CDB"
				},
				"USDC": {
					"apy": 0,
					"apr": 0,
					"tokenSymbol": "USDC"
				},
				"FRAX": {
					"apy": 0,
					"apr": 0,
					"tokenSymbol": "FRAX"
				},
				"MIL": {
					"apy": 0,
					"apr": 0,
					"tokenSymbol": "MIL"
				},
				"XMILADY": {
					"apy": 0,
					"apr": 0,
					"tokenSymbol": "XMILADY"
				},
				"XWIZARD": {
					"apy": 0,
					"apr": 0,
					"tokenSymbol": "XWIZARD"
				},
				"XMILADYWETH": {
					"apy": 0,
					"apr": 0,
					"tokenSymbol": "XMILADYWETH"
				},
				"XWIZARDWETH": {
					"apy": 0,
					"apr": 0,
					"tokenSymbol": "XWIZARDWETH"
				}
			},
			"borrowRates": {
				"ETH": {
					"apy": 0.474117895812672,
					"apr": 0.3944025606998087,
					"tokenSymbol": "ETH"
				},
				"CYBERBROKERS": {
					"apy": 0,
					"apr": 0,
					"tokenSymbol": "CYBERBROKERS"
				},
				"GOBLIN": {
					"apy": 0,
					"apr": 0,
					"tokenSymbol": "GOBLIN"
				},
				"LOBS": {
					"apy": 0,
					"apr": 0,
					"tokenSymbol": "LOBS"
				},
				"TOADZ": {
					"apy": 0,
					"apr": 0,
					"tokenSymbol": "TOADZ"
				},
				"BEANZ": {
					"apy": 0,
					"apr": 0,
					"tokenSymbol": "BEANZ"
				},
				"WIZARDS": {
					"apy": 0,
					"apr": 0,
					"tokenSymbol": "WIZARDS"
				},
				"CDB": {
					"apy": 0,
					"apr": 0,
					"tokenSymbol": "CDB"
				},
				"USDC": {
					"apy": 0.02499999999966,
					"apr": 0.024718035237782487,
					"tokenSymbol": "USDC"
				},
				"FRAX": {
					"apy": 0.02499999999966,
					"apr": 0.024718035237782487,
					"tokenSymbol": "FRAX"
				},
				"MIL": {
					"apy": 0,
					"apr": 0,
					"tokenSymbol": "MIL"
				},
				"XMILADY": {
					"apy": 0.07499999999898,
					"apr": 0.0725390282905467,
					"tokenSymbol": "XMILADY"
				},
				"XWIZARD": {
					"apy": 0.07499999999898,
					"apr": 0.0725390282905467,
					"tokenSymbol": "XWIZARD"
				},
				"XMILADYWETH": {
					"apy": 0.07499999999898,
					"apr": 0.0725390282905467,
					"tokenSymbol": "XMILADYWETH"
				},
				"XWIZARDWETH": {
					"apy": 0.07499999999898,
					"apr": 0.0725390282905467,
					"tokenSymbol": "XWIZARDWETH"
				}
			}
		},
		{
			"id": "0x7312a3bc8733b068989ef44bac6344f07cfcde7f",
			"TVL": 19272.416240249386,
			"totalSupply": 19272.416240249386,
			"totalNFTSupply": 17237.577468732892,
			"totalBorrow": 1.28028622904e-12,
			"markets": {
				"ETH": {
					"id": "0x05231980914B702083B9Ac08002325654F6eb95B",
					"exchangeRate": 0.020707772723426304,
					"supply": 1.0744089707007018,
					"borrow": 6.76e-16,
					"reserves": 0.007534233266409956,
					"priceETH": 1,
					"priceUSD": 1893.91454,
					"cash": 1.081943203967111,
					"cashUSD": 2049.1079654474975,
					"collateralFactor": 0,
					"borrowLimit": 0
				},
				"VFT": {
					"id": "0x780F467401430632ed0529f497C20806b2793dfF",
					"exchangeRate": 100000000,
					"supply": 2,
					"borrow": 0,
					"reserves": 0,
					"priceETH": 1.7,
					"priceUSD": 3219.654718,
					"cash": 2,
					"cashUSD": 6439.309436,
					"collateralFactor": 0.6,
					"borrowLimit": 0.51
				},
				"NOUN": {
					"id": "0x5Ce3d90E359A0F5e841ac8696e736E6EBF8bf2f0",
					"exchangeRate": 100000000,
					"supply": 0,
					"borrow": 0,
					"reserves": 0,
					"priceETH": 27.599999999999998,
					"priceUSD": 52272.041304,
					"cash": 0,
					"cashUSD": 0,
					"collateralFactor": 0,
					"borrowLimit": 0
				},
				"PPG": {
					"id": "0xdA8c9777FEBAb8577a33f4750D165bc13b07B93d",
					"exchangeRate": 100000000,
					"supply": 0,
					"borrow": 0,
					"reserves": 0,
					"priceETH": 3.7487,
					"priceUSD": 7099.717436098,
					"cash": 0,
					"cashUSD": 0,
					"collateralFactor": 0.6,
					"borrowLimit": 0.51
				},
				"COOL": {
					"id": "0x5A5D79e75016330F8b2a02B4f33b5E12003a63D7",
					"exchangeRate": 100000000,
					"supply": 0,
					"borrow": 0,
					"reserves": 0,
					"priceETH": 0.7889123242879151,
					"priceUSD": 1494.1325217540775,
					"cash": 0,
					"cashUSD": 0,
					"collateralFactor": 0,
					"borrowLimit": 0
				},
				"WOW": {
					"id": "0x47919D0b513C88e6ddFEEAD4ea0729c08003dAEE",
					"exchangeRate": 100000000,
					"supply": 14,
					"borrow": 0,
					"reserves": 0,
					"priceETH": 0.4072543101553679,
					"priceUSD": 771.3048594809209,
					"cash": 14,
					"cashUSD": 10798.268032732893,
					"collateralFactor": 0.6,
					"borrowLimit": 0.51
				},
				"USDC": {
					"id": "0x0A494b848d4bE5D58B0fde9f80C9b25592a2D3b2",
					"exchangeRate": 0.02,
					"supply": 0,
					"borrow": 0,
					"reserves": 0,
					"priceETH": 0.0005280069289715681,
					"priceUSD": 1,
					"cash": 0,
					"cashUSD": 0,
					"collateralFactor": 0,
					"borrowLimit": 0
				},
				"FRAX": {
					"id": "0x0039fEc5e1D91741e251d82d9E83859C8E79013d",
					"exchangeRate": 0.02,
					"supply": 0,
					"borrow": 0,
					"reserves": 0,
					"priceETH": 0.0005274780349909558,
					"priceUSD": 0.99899832,
					"cash": 0,
					"cashUSD": 0,
					"collateralFactor": 0,
					"borrowLimit": 0
				}
			},
			"lendRates": {
				"ETH": {
					"apy": 0,
					"apr": 0,
					"tokenSymbol": "ETH"
				},
				"VFT": {
					"apy": 0,
					"apr": 0,
					"tokenSymbol": "VFT"
				},
				"NOUN": {
					"apy": 0,
					"apr": 0,
					"tokenSymbol": "NOUN"
				},
				"PPG": {
					"apy": 0,
					"apr": 0,
					"tokenSymbol": "PPG"
				},
				"COOL": {
					"apy": 0,
					"apr": 0,
					"tokenSymbol": "COOL"
				},
				"WOW": {
					"apy": 0,
					"apr": 0,
					"tokenSymbol": "WOW"
				},
				"USDC": {
					"apy": 0,
					"apr": 0,
					"tokenSymbol": "USDC"
				},
				"FRAX": {
					"apy": 0,
					"apr": 0,
					"tokenSymbol": "FRAX"
				}
			},
			"borrowRates": {
				"ETH": {
					"apy": 0.04999999999932,
					"apr": 0.048889485403130095,
					"tokenSymbol": "ETH"
				},
				"VFT": {
					"apy": 0,
					"apr": 0,
					"tokenSymbol": "VFT"
				},
				"NOUN": {
					"apy": 0,
					"apr": 0,
					"tokenSymbol": "NOUN"
				},
				"PPG": {
					"apy": 0,
					"apr": 0,
					"tokenSymbol": "PPG"
				},
				"COOL": {
					"apy": 0,
					"apr": 0,
					"tokenSymbol": "COOL"
				},
				"WOW": {
					"apy": 0,
					"apr": 0,
					"tokenSymbol": "WOW"
				},
				"USDC": {
					"apy": 0.04999999999932,
					"apr": 0.048889485403130095,
					"tokenSymbol": "USDC"
				},
				"FRAX": {
					"apy": 0.04999999999932,
					"apr": 0.048889485403130095,
					"tokenSymbol": "FRAX"
				}
			}
		},
		{
			"id": "0x3903E6EcD8bc610D5a01061B1Dc31affD21F81C6",
			"TVL": 1433.2881411585868,
			"totalSupply": 1442.7591328457188,
			"totalNFTSupply": 0,
			"totalBorrow": 9.47099168713205,
			"markets": {
				"ETH": {
					"id": "0x588C13e685e44B22DC6647937481C816E5FeE086",
					"exchangeRate": 0.02064231338005953,
					"supply": 0.7617868189795506,
					"borrow": 0.005000749235037844,
					"reserves": 0.019739458116980517,
					"priceETH": 1,
					"priceUSD": 1893.91454,
					"cash": 0.7765255278614932,
					"cashUSD": 1470.672987898057,
					"collateralFactor": 0.85,
					"borrowLimit": 0.7225
				},
				"SQUIGGLES": {
					"id": "0x30C40201f7Af91C1B1EeF6C7b4504669602a82f5",
					"exchangeRate": 100000000,
					"supply": 0,
					"borrow": 0,
					"reserves": 0,
					"priceETH": 10.858411989419531,
					"priceUSD": 20564.904348071977,
					"cash": 0,
					"cashUSD": 0,
					"collateralFactor": 0,
					"borrowLimit": 0
				},
				"USDC": {
					"id": "0xE7D7B65DBe5577d9DA4286367031F5BcCB020674",
					"exchangeRate": 0.02,
					"supply": 0,
					"borrow": 0,
					"reserves": 0,
					"priceETH": 0.0005280069289715681,
					"priceUSD": 1,
					"cash": 0,
					"cashUSD": 0,
					"collateralFactor": 0,
					"borrowLimit": 0
				},
				"FRAX": {
					"id": "0xf00DE3D44228856B2cA1D4550C2eacba153dAca7",
					"exchangeRate": 0.02,
					"supply": 0,
					"borrow": 0,
					"reserves": 0,
					"priceETH": 0.0005274780349909558,
					"priceUSD": 0.99899832,
					"cash": 0,
					"cashUSD": 0,
					"collateralFactor": 0,
					"borrowLimit": 0
				},
				"RINGERS": {
					"id": "0xEf8f2D14104cE88Ad8E1B27C77878c8C9a92bB80",
					"exchangeRate": 100000000,
					"supply": 0,
					"borrow": 0,
					"reserves": 0,
					"priceETH": 42,
					"priceUSD": 79544.41068,
					"cash": 0,
					"cashUSD": 0,
					"collateralFactor": 0,
					"borrowLimit": 0
				},
				"FIDENZA": {
					"id": "0x21897f9694D94F7F3ddCf60FD32b14DB55376b00",
					"exchangeRate": 100000000,
					"supply": 0,
					"borrow": 0,
					"reserves": 0,
					"priceETH": 66,
					"priceUSD": 124998.35964,
					"cash": 0,
					"cashUSD": 0,
					"collateralFactor": 0,
					"borrowLimit": 0
				},
				"XSQGL": {
					"id": "0x8B7cfB541cCfEBFeADb699C5e70550B165383685",
					"exchangeRate": 4.0000000000000004e-11,
					"supply": 0,
					"borrow": 0,
					"reserves": 0,
					"priceETH": 11.520023118706796,
					"priceUSD": 21817.939285654946,
					"cash": 0,
					"cashUSD": 0,
					"collateralFactor": 0,
					"borrowLimit": 0
				},
				"XSQGLWETH": {
					"id": "0x3bFe965147Df3e8BEDf30AD7FE4741bD977f4D06",
					"exchangeRate": 4.0000000000000004e-11,
					"supply": 0,
					"borrow": 0,
					"reserves": 0,
					"priceETH": 6.99538760720218,
					"priceUSD": 13248.666302216017,
					"cash": 0,
					"cashUSD": 0,
					"collateralFactor": 0,
					"borrowLimit": 0
				}
			},
			"lendRates": {
				"ETH": {
					"apy": 0.000231567373692,
					"apr": 0.00023154279991466353,
					"tokenSymbol": "ETH"
				},
				"SQUIGGLES": {
					"apy": 0,
					"apr": 0,
					"tokenSymbol": "SQUIGGLES"
				},
				"USDC": {
					"apy": 0,
					"apr": 0,
					"tokenSymbol": "USDC"
				},
				"FRAX": {
					"apy": 0,
					"apr": 0,
					"tokenSymbol": "FRAX"
				},
				"RINGERS": {
					"apy": 0,
					"apr": 0,
					"tokenSymbol": "RINGERS"
				},
				"FIDENZA": {
					"apy": 0,
					"apr": 0,
					"tokenSymbol": "FIDENZA"
				},
				"XSQGL": {
					"apy": 0,
					"apr": 0,
					"tokenSymbol": "XSQGL"
				},
				"XSQGLWETH": {
					"apy": 0,
					"apr": 0,
					"tokenSymbol": "XSQGLWETH"
				}
			},
			"borrowRates": {
				"ETH": {
					"apy": 0.050393869972452,
					"apr": 0.04926606318554061,
					"tokenSymbol": "ETH"
				},
				"SQUIGGLES": {
					"apy": 0,
					"apr": 0,
					"tokenSymbol": "SQUIGGLES"
				},
				"USDC": {
					"apy": 0.04999999999932,
					"apr": 0.048889485403130095,
					"tokenSymbol": "USDC"
				},
				"FRAX": {
					"apy": 0.04999999999932,
					"apr": 0.048889485403130095,
					"tokenSymbol": "FRAX"
				},
				"RINGERS": {
					"apy": 0,
					"apr": 0,
					"tokenSymbol": "RINGERS"
				},
				"FIDENZA": {
					"apy": 0,
					"apr": 0,
					"tokenSymbol": "FIDENZA"
				},
				"XSQGL": {
					"apy": 0.07499999999898,
					"apr": 0.0725390282905467,
					"tokenSymbol": "XSQGL"
				},
				"XSQGLWETH": {
					"apy": 0.07499999999898,
					"apr": 0.0725390282905467,
					"tokenSymbol": "XSQGLWETH"
				}
			}
		},
		{
			"id": "0x896b8019f5ea3caaAb23cDA0A09B405ed8361E8b",
			"TVL": 389.43942909691367,
			"totalSupply": 390.1099560969169,
			"totalNFTSupply": 284.087181,
			"totalBorrow": 0.6705270000032234,
			"markets": {
				"ETH": {
					"id": "0x777ECcD3fCf4FfA3b12f45a384852608DF2619a0",
					"exchangeRate": 0.02052270811466268,
					"supply": 0.000052839816582822004,
					"borrow": 1.702e-15,
					"reserves": 0.3860845086186163,
					"priceETH": 1,
					"priceUSD": 1893.91454,
					"cash": 0.3861373484351974,
					"cashUSD": 731.3111386384667,
					"collateralFactor": 0,
					"borrowLimit": 0
				},
				"USDC": {
					"id": "0x0eaBea97c25bd4DfcAd294d82404C7DF3b26a2Cc",
					"exchangeRate": 0.0211824666481703,
					"supply": 105.92270099999975,
					"borrow": 0.670527,
					"reserves": 269.250948,
					"priceETH": 0.0005280069289715681,
					"priceUSD": 1,
					"cash": 374.503122,
					"cashUSD": 374.503122,
					"collateralFactor": 0,
					"borrowLimit": 0
				},
				"BAYC": {
					"id": "0x550A4a2bE23c3a78979BBd0C02D588445B385c1b",
					"exchangeRate": 100000000,
					"supply": 0,
					"borrow": 0,
					"reserves": 0,
					"priceETH": 32.68,
					"priceUSD": 61893.1271672,
					"cash": 0,
					"cashUSD": 0,
					"collateralFactor": 0.75,
					"borrowLimit": 0.6375
				},
				"MAYC": {
					"id": "0x6d2527d6cf23016D46Ce7D0F409C59e8E34D0854",
					"exchangeRate": 100000000,
					"supply": 0,
					"borrow": 0,
					"reserves": 0,
					"priceETH": 6.07,
					"priceUSD": 11496.0612578,
					"cash": 0,
					"cashUSD": 0,
					"collateralFactor": 0.75,
					"borrowLimit": 0.6375
				},
				"OTHR": {
					"id": "0xB49655Bc75b61E6482B71c76e269eF8a342283Ba",
					"exchangeRate": 100000000,
					"supply": 0,
					"borrow": 0,
					"reserves": 0,
					"priceETH": 0.6425200000000001,
					"priceUSD": 1216.8779702408,
					"cash": 0,
					"cashUSD": 0,
					"collateralFactor": 0.5,
					"borrowLimit": 0.425
				},
				"BAKC": {
					"id": "0xE751e2e8dcdcB5Ed043419529ba9311Fa7CCDd3E",
					"exchangeRate": 100000000,
					"supply": 0,
					"borrow": 0,
					"reserves": 0,
					"priceETH": 2.3989,
					"priceUSD": 4543.311590005999,
					"cash": 0,
					"cashUSD": 0,
					"collateralFactor": 0.5,
					"borrowLimit": 0.425
				},
				"FRAX": {
					"id": "0xFB0Fceb2f620009C7E29F9e770Ab7CF1d7956ecC",
					"exchangeRate": 0.02,
					"supply": 0,
					"borrow": 0,
					"reserves": 0,
					"priceETH": 0.0005274780349909558,
					"priceUSD": 0.99899832,
					"cash": 0,
					"cashUSD": 0,
					"collateralFactor": 0,
					"borrowLimit": 0
				},
				"MHC": {
					"id": "0xEDAFa6c38ee44810367A77D38D9b99FDAFEE8513",
					"exchangeRate": 100000000,
					"supply": 0,
					"borrow": 0,
					"reserves": 0,
					"priceETH": 0.28,
					"priceUSD": 530.2960712,
					"cash": 0,
					"cashUSD": 0,
					"collateralFactor": 0.7,
					"borrowLimit": 0.595
				},
				"MH": {
					"id": "0x9a045B76beB1713f4bC5e28a2747D1d484dB4DB4",
					"exchangeRate": 100000000,
					"supply": 1,
					"borrow": 0,
					"reserves": 0,
					"priceETH": 0.15,
					"priceUSD": 284.087181,
					"cash": 1,
					"cashUSD": 284.087181,
					"collateralFactor": 0.5,
					"borrowLimit": 0.425
				}
			},
			"lendRates": {
				"ETH": {
					"apy": 0,
					"apr": 0,
					"tokenSymbol": "ETH"
				},
				"USDC": {
					"apy": 0.00013554164916,
					"apr": 0.00013553322959936054,
					"tokenSymbol": "USDC"
				},
				"BAYC": {
					"apy": 0,
					"apr": 0,
					"tokenSymbol": "BAYC"
				},
				"MAYC": {
					"apy": 0,
					"apr": 0,
					"tokenSymbol": "MAYC"
				},
				"OTHR": {
					"apy": 0,
					"apr": 0,
					"tokenSymbol": "OTHR"
				},
				"BAKC": {
					"apy": 0,
					"apr": 0,
					"tokenSymbol": "BAKC"
				},
				"FRAX": {
					"apy": 0,
					"apr": 0,
					"tokenSymbol": "FRAX"
				},
				"MHC": {
					"apy": 0,
					"apr": 0,
					"tokenSymbol": "MHC"
				},
				"MH": {
					"apy": 0,
					"apr": 0,
					"tokenSymbol": "MH"
				}
			},
			"borrowRates": {
				"ETH": {
					"apy": 0.02499999999966,
					"apr": 0.024718035237782487,
					"tokenSymbol": "ETH"
				},
				"USDC": {
					"apy": 0.025189910280468,
					"apr": 0.024903679439295168,
					"tokenSymbol": "USDC"
				},
				"BAYC": {
					"apy": 0,
					"apr": 0,
					"tokenSymbol": "BAYC"
				},
				"MAYC": {
					"apy": 0,
					"apr": 0,
					"tokenSymbol": "MAYC"
				},
				"OTHR": {
					"apy": 0,
					"apr": 0,
					"tokenSymbol": "OTHR"
				},
				"BAKC": {
					"apy": 0,
					"apr": 0,
					"tokenSymbol": "BAKC"
				},
				"FRAX": {
					"apy": 0.02499999999966,
					"apr": 0.024718035237782487,
					"tokenSymbol": "FRAX"
				},
				"MHC": {
					"apy": 0,
					"apr": 0,
					"tokenSymbol": "MHC"
				},
				"MH": {
					"apy": 0,
					"apr": 0,
					"tokenSymbol": "MH"
				}
			}
		},
		{
			"id": "0x48E29b9ddbf3fE6380d7D1ec5b415E97afD14AbB",
			"TVL": 174.99470015378807,
			"totalSupply": 175.03180503407188,
			"totalNFTSupply": 0,
			"totalBorrow": 0.03710488028379467,
			"markets": {
				"AURAWSTETHETH": {
					"id": "0x1a84831Ac2c42613c6eBb079aE8Bd01335b6207e",
					"exchangeRate": 0.020000000060639116,
					"supply": 0.047581176944264024,
					"borrow": 0,
					"reserves": 0,
					"priceETH": 1.0365546768053706,
					"priceUSD": 1963.145973906692,
					"cash": 0.047581176944264024,
					"cashUSD": 93.40879595187384,
					"collateralFactor": 0.8,
					"borrowLimit": 0.68
				},
				"YVUSDC": {
					"id": "0xA3a1A7598060Ac3ca11d7604019F3fFc32bCE7Ec",
					"exchangeRate": 0.0200001498679592,
					"supply": 3.953402999999989,
					"borrow": 0.0359,
					"reserves": 0.000004,
					"priceETH": 0.000545727963468081,
					"priceUSD": 1.0335621248967874,
					"cash": 3.917507,
					"cashUSD": 4.048986859218039,
					"collateralFactor": 0.8,
					"borrowLimit": 0.68
				},
				"GOHM": {
					"id": "0xb97A79FcbC3867Bb68247F5f76359448ed3eBCa3",
					"exchangeRate": 2e-14,
					"supply": 0.02734152751672077,
					"borrow": 0,
					"reserves": 0,
					"priceETH": 1.4973571526285145,
					"priceUSD": 2835.866482936143,
					"cash": 0.02734152751672077,
					"cashUSD": 77.5369214769447,
					"collateralFactor": 0.8,
					"borrowLimit": 0.68
				},
				"YVDAI": {
					"id": "0x367144a75577f7FBE80E69854046F6169eF080aC",
					"exchangeRate": 2e-14,
					"supply": 0,
					"borrow": 0,
					"reserves": 0,
					"priceETH": 0.000556642608360624,
					"priceUSD": 1.0542335295577114,
					"cash": 0,
					"cashUSD": 0,
					"collateralFactor": 0.8,
					"borrowLimit": 0.68
				},
				"YVWETH": {
					"id": "0x72ab6843D4c988D74Dd8D5cdF16eF49301d87952",
					"exchangeRate": 2e-14,
					"supply": 0,
					"borrow": 0,
					"reserves": 0,
					"priceETH": 1.0411900349773522,
					"priceUSD": 1971.9249461467157,
					"cash": 0,
					"cashUSD": 0,
					"collateralFactor": 0.8,
					"borrowLimit": 0.68
				},
				"YVUSDT": {
					"id": "0xF63f89F6463550Ce4ce5B6Ca6b1323B39C90E9cB",
					"exchangeRate": 0.02,
					"supply": 0,
					"borrow": 0,
					"reserves": 0,
					"priceETH": 0.000536197655918984,
					"priceUSD": 1.0155125368588809,
					"cash": 0,
					"cashUSD": 0,
					"collateralFactor": 0.8,
					"borrowLimit": 0.68
				},
				"DAURAWSTETHRETHSFRXETH": {
					"id": "0xa2EDFd267e9e2f76cd54bD720927a176FAdC19A8",
					"exchangeRate": 0.02,
					"supply": 0,
					"borrow": 0,
					"reserves": 0,
					"priceETH": 1.014381580200621,
					"priceUSD": 1921.1520238501325,
					"cash": 0,
					"cashUSD": 0,
					"collateralFactor": 0.8,
					"borrowLimit": 0.68
				},
				"DAURARETHETH": {
					"id": "0x04a083C48EAAC049964129e5a3eF7d48e0f7a7e7",
					"exchangeRate": 0.02,
					"supply": 0,
					"borrow": 0,
					"reserves": 0,
					"priceETH": 1.024674905136727,
					"priceUSD": 1940.646701611568,
					"cash": 0,
					"cashUSD": 0,
					"collateralFactor": 0.8,
					"borrowLimit": 0.68
				}
			},
			"lendRates": {
				"AURAWSTETHETH": {
					"apy": 0,
					"apr": 0,
					"tokenSymbol": "AURAWSTETHETH"
				},
				"YVUSDC": {
					"apy": 0.00001385167554,
					"apr": 0.000013851587599589266,
					"tokenSymbol": "YVUSDC"
				},
				"GOHM": {
					"apy": 0,
					"apr": 0,
					"tokenSymbol": "GOHM"
				},
				"YVDAI": {
					"apy": 0,
					"apr": 0,
					"tokenSymbol": "YVDAI"
				},
				"YVWETH": {
					"apy": 0,
					"apr": 0,
					"tokenSymbol": "YVWETH"
				},
				"YVUSDT": {
					"apy": 0,
					"apr": 0,
					"tokenSymbol": "YVUSDT"
				},
				"DAURAWSTETHRETHSFRXETH": {
					"apy": 0,
					"apr": 0,
					"tokenSymbol": "DAURAWSTETHRETHSFRXETH"
				},
				"DAURARETHETH": {
					"apy": 0,
					"apr": 0,
					"tokenSymbol": "DAURARETHETH"
				}
			},
			"borrowRates": {
				"AURAWSTETHETH": {
					"apy": 0,
					"apr": 0,
					"tokenSymbol": "AURAWSTETHETH"
				},
				"YVUSDC": {
					"apy": 0.001794568626072,
					"apr": 0.001793094264444406,
					"tokenSymbol": "YVUSDC"
				},
				"GOHM": {
					"apy": 0.000999999997884,
					"apr": 0.0009995419571628972,
					"tokenSymbol": "GOHM"
				},
				"YVDAI": {
					"apy": 0.000999999997884,
					"apr": 0.0009995419571628972,
					"tokenSymbol": "YVDAI"
				},
				"YVWETH": {
					"apy": 0.000999999997884,
					"apr": 0.0009995419571628972,
					"tokenSymbol": "YVWETH"
				},
				"YVUSDT": {
					"apy": 0.000999999997884,
					"apr": 0.0009995419571628972,
					"tokenSymbol": "YVUSDT"
				},
				"DAURAWSTETHRETHSFRXETH": {
					"apy": 0.000999999997884,
					"apr": 0.0009995419571628972,
					"tokenSymbol": "DAURAWSTETHRETHSFRXETH"
				},
				"DAURARETHETH": {
					"apy": 0.000999999997884,
					"apr": 0.0009995419571628972,
					"tokenSymbol": "DAURARETHETH"
				}
			}
		}
	]
}